educelab/hercdb/__init__.py
educelab/hercdb/api.py
educelab/hercdb/config.py
educelab/hercdb/apps/__init__.py
educelab/hercdb/apps/search.py
educelab_hercdb-0.1.1.dist-info/METADATA
educelab_hercdb-0.1.1.dist-info/WHEEL
educelab_hercdb-0.1.1.dist-info/entry_points.txt
educelab_hercdb-0.1.1.dist-info/top_level.txt
educelab_hercdb-0.1.1.dist-info/RECORD
